sources/__init__.py
sources/sekiryu.py
sources/modules/__init__.py
sources/modules/cli.py
sources/modules/ghidra_pilot.py
sources/modules/pcode.py
sources/modules/report.py
sources/modules/server.py
sources/modules/sgrep.py
sources/modules/vuln_search.py
sources/modules/rules_sgrep/__init__.py
sources/modules/rules_sgrep/argv-envp-access.yaml
sources/modules/rules_sgrep/bad-words.yaml
sources/modules/rules_sgrep/command-injection.yaml
sources/modules/rules_sgrep/double-free.yaml
sources/modules/rules_sgrep/format-string-bugs.yaml
sources/modules/rules_sgrep/incorrect-order-setuid-setgid-etc.yaml
sources/modules/rules_sgrep/incorrect-unsigned-comparison.yaml
sources/modules/rules_sgrep/incorrect-use-of-sizeof.yaml
sources/modules/rules_sgrep/incorrect-use-of-strncat.yaml
sources/modules/rules_sgrep/incorrect-use-of-strncpy-stpncpy-strlcpy.yaml
sources/modules/rules_sgrep/insecure-api-access-stat-lstat.yaml
sources/modules/rules_sgrep/insecure-api-alloca.yaml
sources/modules/rules_sgrep/insecure-api-atoi-atol-atof.yaml
sources/modules/rules_sgrep/insecure-api-gets.yaml
sources/modules/rules_sgrep/insecure-api-mktemp-tmpnam-tempnam.yaml
sources/modules/rules_sgrep/insecure-api-rand-srand.yaml
sources/modules/rules_sgrep/insecure-api-scanf-etc.yaml
sources/modules/rules_sgrep/insecure-api-sprintf-vsprintf.yaml
sources/modules/rules_sgrep/insecure-api-strcpy-stpcpy-strcat.yaml
sources/modules/rules_sgrep/integer-truncation.yaml
sources/modules/rules_sgrep/integer-wraparound.yaml
sources/modules/rules_sgrep/interesting-api-calls.yaml
sources/modules/rules_sgrep/memory-address-exposure.yaml
sources/modules/rules_sgrep/mismatched-memory-management-cpp.cpp
sources/modules/rules_sgrep/mismatched-memory-management-cpp.yaml
sources/modules/rules_sgrep/mismatched-memory-management.yaml
sources/modules/rules_sgrep/missing-break-in-switch.yaml
sources/modules/rules_sgrep/missing-default-in-switch.yaml
sources/modules/rules_sgrep/off-by-one.yaml
sekiryu-0.0.2.1.dist-info/LICENSE
sekiryu-0.0.2.1.dist-info/METADATA
sekiryu-0.0.2.1.dist-info/WHEEL
sekiryu-0.0.2.1.dist-info/entry_points.txt
sekiryu-0.0.2.1.dist-info/top_level.txt
sekiryu-0.0.2.1.dist-info/RECORD
